Workbook

Sheet Tableau de bord
A1: Ma Paie
A2: Choisis le mois en B3. Tout le reste se calcule.
A3: Mois affiché | B3: 2026-10
A5: =IF(A6<0,"DÉPASSEMENT","RESTE À VIVRE")&IF(INDEX(Mois!$B$5:$B$40,MATCH($B$3,Mois!$A$5:$A$40,0))=""," (théorique : salaire estimé)","") -> RESTE À VIVRE (théorique : salaire estimé) | D5: Alertes | G5: Dépenses du mois par catégorie
A6: =IFERROR(INDEX(Mois!$Q$5:$Q$40,MATCH($B$3,Mois!$A$5:$A$40,0)),0) -> 764.97 | D6: =IFERROR(IF(B17<0,"🔴 Budget dépassé de "&FIXED(-B17,2)&" € : limite-toi à l’essentiel.",""),"") | G6: Catégorie | H6: Montant
A7: =IFERROR(IF(INDEX(Mois!$B$5:$B$40,MATCH($B$3,Mois!$A$5:$A$40,0))="","≈ Salaire estimé : "&FIXED(INDEX(Mois!$H$5:$H$40,MATCH($B$3,Mois!$A$5:$A$40,0)),2)&" € · pas encore reçu","✓ Salaire reçu : "&FIXED(INDEX(Mois!$B$5:$B$40,MATCH($B$3,Mois!$A$5:$A$40,0)),2)&" €"),"") -> ≈ Salaire estimé : 1,494.97 € · pas encore reçu | D7: =IFERROR(IF(B14<0,"🔴 Charges + épargne dépassent le salaire : baisse l’épargne du mois.",""),"") | G7: =IF(Paramètres!A22="","",Paramètres!A22) -> Transport | H7: =IF(G7="","",SUMIFS(Dépenses!$B$5:$B$504,Dépenses!$E$5:$E$504,$B$3,Dépenses!$C$5:$C$504,G7)) -> 0
A8: Comment le reste à vivre est calculé | D8: =IFERROR(IF(AND(B14>=0,B14<300),"🟠 Budget serré : moins de 300 € pour vivre.",""),"") | G8: =IF(Paramètres!A23="","",Paramètres!A23) -> Courses | H8: =IF(G8="","",SUMIFS(Dépenses!$B$5:$B$504,Dépenses!$E$5:$E$504,$B$3,Dépenses!$C$5:$C$504,G8)) -> 50
A9: Salaire du mois | B9: =IFERROR(INDEX(Mois!$I$5:$I$40,MATCH($B$3,Mois!$A$5:$A$40,0)),0) -> 1494.97 | D9: =IFERROR(IF(INDEX(Mois!$B$5:$B$40,MATCH($B$3,Mois!$A$5:$A$40,0))="","🟠 Salaire non saisi : les montants sont théoriques.",""),"") -> 🟠 Salaire non saisi : les montants sont théoriques. | G9: =IF(Paramètres!A24="","",Paramètres!A24) -> Restaurants | H9: =IF(G9="","",SUMIFS(Dépenses!$B$5:$B$504,Dépenses!$E$5:$E$504,$B$3,Dépenses!$C$5:$C$504,G9)) -> 30
A10: − Charges fixes | B10: =IFERROR(-INDEX(Mois!$K$5:$K$40,MATCH($B$3,Mois!$A$5:$A$40,0)),0) -> -470 | D10: =IFERROR(IF(B11>0,"🔵 "&FIXED(B11,2)&" € de charges encore à payer : garde l’argent sur le compte.",""),"") -> 🔵 20.00 € de charges encore à payer : garde l’argent sur le compte. | G10: =IF(Paramètres!A25="","",Paramètres!A25) -> Divertissement | H10: =IF(G10="","",SUMIFS(Dépenses!$B$5:$B$504,Dépenses!$E$5:$E$504,$B$3,Dépenses!$C$5:$C$504,G10)) -> 0
A11: dont encore à payer | B11: =IFERROR(INDEX(Mois!$K$5:$K$40,MATCH($B$3,Mois!$A$5:$A$40,0))-INDEX(Mois!$L$5:$L$40,MATCH($B$3,Mois!$A$5:$A$40,0)),0) -> 20 | D11: =IFERROR(IF(Épargne!J4<-0.004,"🔴 Objectifs : plus d’argent affecté que d’épargne.",""),"") | G11: =IF(Paramètres!A26="","",Paramètres!A26) -> Achats | H11: =IF(G11="","",SUMIFS(Dépenses!$B$5:$B$504,Dépenses!$E$5:$E$504,$B$3,Dépenses!$C$5:$C$504,G11)) -> 80
A12: − Épargne du mois | B12: =IFERROR(-INDEX(Mois!$N$5:$N$40,MATCH($B$3,Mois!$A$5:$A$40,0)),0) -> -100 | D12: =IF(COUNTBLANK(D6:D11)=6,"✓ Rien à signaler","") | G12: =IF(Paramètres!A27="","",Paramètres!A27) -> Argent de poche | H12: =IF(G12="","",SUMIFS(Dépenses!$B$5:$B$504,Dépenses!$E$5:$E$504,$B$3,Dépenses!$C$5:$C$504,G12)) -> 0
A13: dont déjà versée | B13: =IFERROR(INDEX(Mois!$M$5:$M$40,MATCH($B$3,Mois!$A$5:$A$40,0)),0) -> 100 | G13: =IF(Paramètres!A28="","",Paramètres!A28) -> Santé | H13: =IF(G13="","",SUMIFS(Dépenses!$B$5:$B$504,Dépenses!$E$5:$E$504,$B$3,Dépenses!$C$5:$C$504,G13)) -> 0
A14: → Budget pour vivre | B14: =IFERROR(INDEX(Mois!$I$5:$I$40,MATCH($B$3,Mois!$A$5:$A$40,0))-INDEX(Mois!$K$5:$K$40,MATCH($B$3,Mois!$A$5:$A$40,0))-INDEX(Mois!$N$5:$N$40,MATCH($B$3,Mois!$A$5:$A$40,0)),0) -> 924.97 | D14: Épargne | G14: =IF(Paramètres!A29="","",Paramètres!A29) -> Général | H14: =IF(G14="","",SUMIFS(Dépenses!$B$5:$B$504,Dépenses!$E$5:$E$504,$B$3,Dépenses!$C$5:$C$504,G14)) -> 0
A15: − Dépenses déjà faites | B15: =IFERROR(-INDEX(Mois!$P$5:$P$40,MATCH($B$3,Mois!$A$5:$A$40,0)),0) -> -80 | D15: Épargne totale | E15: =Épargne!B4 -> 600 | G15: =IF(Paramètres!A30="","",Paramètres!A30) | H15: =IF(G15="","",SUMIFS(Dépenses!$B$5:$B$504,Dépenses!$E$5:$E$504,$B$3,Dépenses!$C$5:$C$504,G15))
A16: − Dépenses prévues | B16: =IFERROR(-(INDEX(Mois!$O$5:$O$40,MATCH($B$3,Mois!$A$5:$A$40,0))-INDEX(Mois!$P$5:$P$40,MATCH($B$3,Mois!$A$5:$A$40,0))),0) -> -80 | D16: Affectée aux objectifs | E16: =Épargne!F4 -> 500 | G16: =IF(Paramètres!A31="","",Paramètres!A31) | H16: =IF(G16="","",SUMIFS(Dépenses!$B$5:$B$504,Dépenses!$E$5:$E$504,$B$3,Dépenses!$C$5:$C$504,G16))
A17: → Reste à vivre | B17: =IFERROR(INDEX(Mois!$Q$5:$Q$40,MATCH($B$3,Mois!$A$5:$A$40,0)),0) -> 764.97 | D17: Libre | E17: =Épargne!J4 -> 100 | G17: =IF(Paramètres!A32="","",Paramètres!A32) | H17: =IF(G17="","",SUMIFS(Dépenses!$B$5:$B$504,Dépenses!$E$5:$E$504,$B$3,Dépenses!$C$5:$C$504,G17))
G18: =IF(Paramètres!A33="","",Paramètres!A33) | H18: =IF(G18="","",SUMIFS(Dépenses!$B$5:$B$504,Dépenses!$E$5:$E$504,$B$3,Dépenses!$C$5:$C$504,G18))
A19: Par jour conseillé | B19: =IFERROR(IF(AND($B$3=Paramètres!$B$4,B17>0),ROUNDDOWN(B17/(DAY(EOMONTH(TODAY(),0))-DAY(TODAY())+1),2),"—"),"—") -> 47.81 | G19: =IF(Paramètres!A34="","",Paramètres!A34) | H19: =IF(G19="","",SUMIFS(Dépenses!$B$5:$B$504,Dépenses!$E$5:$E$504,$B$3,Dépenses!$C$5:$C$504,G19))
A20: Uniquement pour le mois en cours, aujourd’hui compris. | G20: =IF(Paramètres!A35="","",Paramètres!A35) | H20: =IF(G20="","",SUMIFS(Dépenses!$B$5:$B$504,Dépenses!$E$5:$E$504,$B$3,Dépenses!$C$5:$C$504,G20))
G21: =IF(Paramètres!A36="","",Paramètres!A36) | H21: =IF(G21="","",SUMIFS(Dépenses!$B$5:$B$504,Dépenses!$E$5:$E$504,$B$3,Dépenses!$C$5:$C$504,G21))
G22: =IF(Paramètres!A37="","",Paramètres!A37) | H22: =IF(G22="","",SUMIFS(Dépenses!$B$5:$B$504,Dépenses!$E$5:$E$504,$B$3,Dépenses!$C$5:$C$504,G22))

Sheet Paramètres
A1: Paramètres
A2: Texte bleu = valeur à saisir. Texte noir = calcul automatique.
A4: Mois en cours (automatique) | B4: =YEAR(TODAY())&"-"&TEXT(MONTH(TODAY()),"00") -> 2026-10 | C4: Calculé à partir de la date du jour.
A5: Épargne déjà constituée avant le suivi | B5: 500 | C5: Saisie par toi. Compte dans l’épargne totale.
A6: Objectif d’épargne par mois | B6: 300 | C6: Valeur par défaut des nouveaux mois.
A7: Début de l’épargne (AAAA-MM) | B7: 2026-11 | C7: Texte au format 2026-11.
A8: — Paie (fiche de septembre 2026, à vérifier) —
A9: Salaire de base brut | B9: 1493.65 | C9: Fiche de paie de septembre 2026.
A10: Part soumise du panier / jour | B10: 1.45 | C10: Fiche de septembre 2026 — à confirmer.
A11: Indemnité de trajet / jour | B11: 2.13 | C11: Fiche de septembre 2026 — à confirmer.
A12: Panier non soumis / jour | B12: 10.4 | C12: Ajouté au net, sans cotisations.
A13: Taux horaire de retenue d’absence | B13: 9.699 | C13: Différent de base ÷ 151,67 h (9,848 €/h) : à vérifier.
A14: Heures par jour d’absence | B14: 7
A15: Cotisations de référence | B15: 172.7 | C15: Pour le brut de référence ci-dessous.
A16: Brut de référence | B16: 1382.92 | C16: Plus bas que le salaire de base : absence ou prorata en septembre ? À confirmer.
A17: Taux marginal de cotisations | B17: 0.217 | C17: Approximation linéaire (les exonérations apprentis ne sont pas linéaires).
A20: Catégories de dépenses
A21: Catégorie | B21: Budget / mois
A22: Transport | B22: 120
A23: Courses | B23: 200
A24: Restaurants | B24: 60
A25: Divertissement
A26: Achats
A27: Argent de poche
A28: Santé
A29: Général
A38: (lignes libres jusqu’à la ligne 37 pour ajouter des catégories)

Sheet Dépenses
A1: Dépenses
A2: Une ligne par dépense. Une date future = dépense prévue (pas encore payée).
A4: Date | B4: Montant | C4: Catégorie | D4: Détail | E4: Mois | F4: Statut
A5: 46268 | B5: 40 | C5: Courses | D5: Supermarché | E5: =IF(A5="","",YEAR(A5)&"-"&TEXT(MONTH(A5),"00")) -> 2026-09 | F5: =IF(A5="","",IF(A5<=TODAY(),"Payée","Prévue")) -> Payée
A6: 46275 | B6: 35 | C6: Transport | D6: Plein | E6: =IF(A6="","",YEAR(A6)&"-"&TEXT(MONTH(A6),"00")) -> 2026-09 | F6: =IF(A6="","",IF(A6<=TODAY(),"Payée","Prévue")) -> Payée
A7: 46285 | B7: 20 | C7: Restaurants | D7: Midi | E7: =IF(A7="","",YEAR(A7)&"-"&TEXT(MONTH(A7),"00")) -> 2026-09 | F7: =IF(A7="","",IF(A7<=TODAY(),"Payée","Prévue")) -> Payée
A8: 46298 | B8: 50 | C8: Courses | D8: Supermarché | E8: =IF(A8="","",YEAR(A8)&"-"&TEXT(MONTH(A8),"00")) -> 2026-10 | F8: =IF(A8="","",IF(A8<=TODAY(),"Payée","Prévue")) -> Payée
A9: 46307 | B9: 30 | C9: Restaurants | D9: Anniversaire | E9: =IF(A9="","",YEAR(A9)&"-"&TEXT(MONTH(A9),"00")) -> 2026-10 | F9: =IF(A9="","",IF(A9<=TODAY(),"Payée","Prévue")) -> Payée
A10: 46323 | B10: 80 | C10: Achats | D10: Cadeau (prévu) | E10: =IF(A10="","",YEAR(A10)&"-"&TEXT(MONTH(A10),"00")) -> 2026-10 | F10: =IF(A10="","",IF(A10<=TODAY(),"Payée","Prévue")) -> Prévue
E11: =IF(A11="","",YEAR(A11)&"-"&TEXT(MONTH(A11),"00")) | F11: =IF(A11="","",IF(A11<=TODAY(),"Payée","Prévue"))
E12: =IF(A12="","",YEAR(A12)&"-"&TEXT(MONTH(A12),"00")) | F12: =IF(A12="","",IF(A12<=TODAY(),"Payée","Prévue"))
E13: =IF(A13="","",YEAR(A13)&"-"&TEXT(MONTH(A13),"00")) | F13: =IF(A13="","",IF(A13<=TODAY(),"Payée","Prévue"))
E14: =IF(A14="","",YEAR(A14)&"-"&TEXT(MONTH(A14),"00")) | F14: =IF(A14="","",IF(A14<=TODAY(),"Payée","Prévue"))
E15: =IF(A15="","",YEAR(A15)&"-"&TEXT(MONTH(A15),"00")) | F15: =IF(A15="","",IF(A15<=TODAY(),"Payée","Prévue"))
E16: =IF(A16="","",YEAR(A16)&"-"&TEXT(MONTH(A16),"00")) | F16: =IF(A16="","",IF(A16<=TODAY(),"Payée","Prévue"))
E17: =IF(A17="","",YEAR(A17)&"-"&TEXT(MONTH(A17),"00")) | F17: =IF(A17="","",IF(A17<=TODAY(),"Payée","Prévue"))
E18: =IF(A18="","",YEAR(A18)&"-"&TEXT(MONTH(A18),"00")) | F18: =IF(A18="","",IF(A18<=TODAY(),"Payée","Prévue"))
E19: =IF(A19="","",YEAR(A19)&"-"&TEXT(MONTH(A19),"00")) | F19: =IF(A19="","",IF(A19<=TODAY(),"Payée","Prévue"))
E20: =IF(A20="","",YEAR(A20)&"-"&TEXT(MONTH(A20),"00")) | F20: =IF(A20="","",IF(A20<=TODAY(),"Payée","Prévue"))
E21: =IF(A21="","",YEAR(A21)&"-"&TEXT(MONTH(A21),"00")) | F21: =IF(A21="","",IF(A21<=TODAY(),"Payée","Prévue"))
E22: =IF(A22="","",YEAR(A22)&"-"&TEXT(MONTH(A22),"00")) | F22: =IF(A22="","",IF(A22<=TODAY(),"Payée","Prévue"))
... E504: =IF(A504="","",YEAR(A504)&"-"&TEXT(MONTH(A504),"00")) | F504: =IF(A504="","",IF(A504<=TODAY(),"Payée","Prévue"))

Sheet Charges
A1: Charges fixes
A2: Une ligne par charge et par mois. « Payée » = Oui quand elle est prélevée.
A4: Mois | B4: Charge | C4: Montant | D4: Jour | E4: Payée
A5: 2026-09 | B5: Loyer | C5: 450 | D5: 5 | E5: Oui
A6: 2026-09 | B6: Forfait téléphone | C6: 20 | D6: 25 | E6: Oui
A7: 2026-10 | B7: Loyer | C7: 450 | D7: 5 | E7: Oui
A8: 2026-10 | B8: Forfait téléphone | C8: 20 | D8: 25 | E8: Non
A9: 2026-11 | B9: Loyer | C9: 450 | D9: 5 | E9: Non
A10: 2026-11 | B10: Forfait téléphone | C10: 20 | D10: 25 | E10: Non
A11: 2026-12 | B11: Loyer | C11: 450 | D11: 5 | E11: Non
A12: 2026-12 | B12: Forfait téléphone | C12: 20 | D12: 25 | E12: Non
A13: 2027-01 | B13: Loyer | C13: 450 | D13: 5 | E13: Non
A14: 2027-01 | B14: Forfait téléphone | C14: 20 | D14: 25 | E14: Non
A15: 2027-02 | B15: Loyer | C15: 450 | D15: 5 | E15: Non
A16: 2027-02 | B16: Forfait téléphone | C16: 20 | D16: 25 | E16: Non

Sheet Épargne
A1: Épargne
A2: Totale = départ + versements − argent utilisé. Affectée = part réservée aux objectifs (pas de l’argent en plus). Libre = le reste.
A4: Épargne totale | B4: =Paramètres!$B$5+SUM(C8:C507)-SUM(G8:G507) -> 600 | E4: Affectée aux objectifs | F4: =SUM(K8:K40) -> 500 | I4: Épargne libre | J4: =B4-F4 -> 100
A5: =IF(J4<-0.004,"⚠ Plus d’argent affecté aux objectifs que d’épargne : manque "&FIXED(-J4,2)&" €. Retire de l’argent d’un objectif (mouvement négatif).","")
A6: Versements | E6: Argent utilisé (retraits) | I6: Objectifs | Q6: Mouvements des objectifs (+ affecter / − retirer)
A7: Date | B7: Mois | C7: Montant | E7: Date | F7: Motif | G7: Montant | I7: Objectif | J7: Cible | K7: Affecté | L7: Restant | M7: % | N7: Date limite | O7: État | Q7: Objectif | R7: Montant | S7: Note
A8: 46297 | B8: =IF(A8="","",YEAR(A8)&"-"&TEXT(MONTH(A8),"00")) -> 2026-10 | C8: 100 | I8: Permis de conduire | J8: 1200 | K8: =IF(I8="","",SUMIFS($R$8:$R$507,$Q$8:$Q$507,I8)) -> 300 | L8: =IF(I8="","",MAX(0,J8-K8)) -> 900 | M8: =IF(OR(I8="",N(J8)<=0),"",MIN(1,MAX(0,K8/J8))) -> 0.25 | N8: 46568 | O8: =IF(I8="","",IF(K8>=J8,"Atteint ✓",IF(AND(N8<>"",N8<TODAY()),"Date dépassée","En cours"))) -> En cours | Q8: Permis de conduire | R8: 300 | S8: Déjà économisé au départ
B9: =IF(A9="","",YEAR(A9)&"-"&TEXT(MONTH(A9),"00")) | I9: Vacances | J9: 600 | K9: =IF(I9="","",SUMIFS($R$8:$R$507,$Q$8:$Q$507,I9)) -> 200 | L9: =IF(I9="","",MAX(0,J9-K9)) -> 400 | M9: =IF(OR(I9="",N(J9)<=0),"",MIN(1,MAX(0,K9/J9))) -> 0.33333333 | O9: =IF(I9="","",IF(K9>=J9,"Atteint ✓",IF(AND(N9<>"",N9<TODAY()),"Date dépassée","En cours"))) -> En cours | Q9: Vacances | R9: 200 | S9: Déjà économisé au départ
B10: =IF(A10="","",YEAR(A10)&"-"&TEXT(MONTH(A10),"00")) | K10: =IF(I10="","",SUMIFS($R$8:$R$507,$Q$8:$Q$507,I10)) | L10: =IF(I10="","",MAX(0,J10-K10)) | M10: =IF(OR(I10="",N(J10)<=0),"",MIN(1,MAX(0,K10/J10))) | O10: =IF(I10="","",IF(K10>=J10,"Atteint ✓",IF(AND(N10<>"",N10<TODAY()),"Date dépassée","En cours")))
B11: =IF(A11="","",YEAR(A11)&"-"&TEXT(MONTH(A11),"00")) | K11: =IF(I11="","",SUMIFS($R$8:$R$507,$Q$8:$Q$507,I11)) | L11: =IF(I11="","",MAX(0,J11-K11)) | M11: =IF(OR(I11="",N(J11)<=0),"",MIN(1,MAX(0,K11/J11))) | O11: =IF(I11="","",IF(K11>=J11,"Atteint ✓",IF(AND(N11<>"",N11<TODAY()),"Date dépassée","En cours")))
B12: =IF(A12="","",YEAR(A12)&"-"&TEXT(MONTH(A12),"00")) | K12: =IF(I12="","",SUMIFS($R$8:$R$507,$Q$8:$Q$507,I12)) | L12: =IF(I12="","",MAX(0,J12-K12)) | M12: =IF(OR(I12="",N(J12)<=0),"",MIN(1,MAX(0,K12/J12))) | O12: =IF(I12="","",IF(K12>=J12,"Atteint ✓",IF(AND(N12<>"",N12<TODAY()),"Date dépassée","En cours")))
B13: =IF(A13="","",YEAR(A13)&"-"&TEXT(MONTH(A13),"00")) | K13: =IF(I13="","",SUMIFS($R$8:$R$507,$Q$8:$Q$507,I13)) | L13: =IF(I13="","",MAX(0,J13-K13)) | M13: =IF(OR(I13="",N(J13)<=0),"",MIN(1,MAX(0,K13/J13))) | O13: =IF(I13="","",IF(K13>=J13,"Atteint ✓",IF(AND(N13<>"",N13<TODAY()),"Date dépassée","En cours")))
B14: =IF(A14="","",YEAR(A14)&"-"&TEXT(MONTH(A14),"00")) | K14: =IF(I14="","",SUMIFS($R$8:$R$507,$Q$8:$Q$507,I14)) | L14: =IF(I14="","",MAX(0,J14-K14)) | M14: =IF(OR(I14="",N(J14)<=0),"",MIN(1,MAX(0,K14/J14))) | O14: =IF(I14="","",IF(K14>=J14,"Atteint ✓",IF(AND(N14<>"",N14<TODAY()),"Date dépassée","En cours")))
B15: =IF(A15="","",YEAR(A15)&"-"&TEXT(MONTH(A15),"00")) | K15: =IF(I15="","",SUMIFS($R$8:$R$507,$Q$8:$Q$507,I15)) | L15: =IF(I15="","",MAX(0,J15-K15)) | M15: =IF(OR(I15="",N(J15)<=0),"",MIN(1,MAX(0,K15/J15))) | O15: =IF(I15="","",IF(K15>=J15,"Atteint ✓",IF(AND(N15<>"",N15<TODAY()),"Date dépassée","En cours")))
B16: =IF(A16="","",YEAR(A16)&"-"&TEXT(MONTH(A16),"00")) | K16: =IF(I16="","",SUMIFS($R$8:$R$507,$Q$8:$Q$507,I16)) | L16: =IF(I16="","",MAX(0,J16-K16)) | M16: =IF(OR(I16="",N(J16)<=0),"",MIN(1,MAX(0,K16/J16))) | O16: =IF(I16="","",IF(K16>=J16,"Atteint ✓",IF(AND(N16<>"",N16<TODAY()),"Date dépassée","En cours")))
B17: =IF(A17="","",YEAR(A17)&"-"&TEXT(MONTH(A17),"00")) | K17: =IF(I17="","",SUMIFS($R$8:$R$507,$Q$8:$Q$507,I17)) | L17: =IF(I17="","",MAX(0,J17-K17)) | M17: =IF(OR(I17="",N(J17)<=0),"",MIN(1,MAX(0,K17/J17))) | O17: =IF(I17="","",IF(K17>=J17,"Atteint ✓",IF(AND(N17<>"",N17<TODAY()),"Date dépassée","En cours")))
B18: =IF(A18="","",YEAR(A18)&"-"&TEXT(MONTH(A18),"00")) | K18: =IF(I18="","",SUMIFS($R$8:$R$507,$Q$8:$Q$507,I18)) | L18: =IF(I18="","",MAX(0,J18-K18)) | M18: =IF(OR(I18="",N(J18)<=0),"",MIN(1,MAX(0,K18/J18))) | O18: =IF(I18="","",IF(K18>=J18,"Atteint ✓",IF(AND(N18<>"",N18<TODAY()),"Date dépassée","En cours")))
B19: =IF(A19="","",YEAR(A19)&"-"&TEXT(MONTH(A19),"00")) | K19: =IF(I19="","",SUMIFS($R$8:$R$507,$Q$8:$Q$507,I19)) | L19: =IF(I19="","",MAX(0,J19-K19)) | M19: =IF(OR(I19="",N(J19)<=0),"",MIN(1,MAX(0,K19/J19))) | O19: =IF(I19="","",IF(K19>=J19,"Atteint ✓",IF(AND(N19<>"",N19<TODAY()),"Date dépassée","En cours")))
B20: =IF(A20="","",YEAR(A20)&"-"&TEXT(MONTH(A20),"00")) | K20: =IF(I20="","",SUMIFS($R$8:$R$507,$Q$8:$Q$507,I20)) | L20: =IF(I20="","",MAX(0,J20-K20)) | M20: =IF(OR(I20="",N(J20)<=0),"",MIN(1,MAX(0,K20/J20))) | O20: =IF(I20="","",IF(K20>=J20,"Atteint ✓",IF(AND(N20<>"",N20<TODAY()),"Date dépassée","En cours")))
B21: =IF(A21="","",YEAR(A21)&"-"&TEXT(MONTH(A21),"00")) | K21: =IF(I21="","",SUMIFS($R$8:$R$507,$Q$8:$Q$507,I21)) | L21: =IF(I21="","",MAX(0,J21-K21)) | M21: =IF(OR(I21="",N(J21)<=0),"",MIN(1,MAX(0,K21/J21))) | O21: =IF(I21="","",IF(K21>=J21,"Atteint ✓",IF(AND(N21<>"",N21<TODAY()),"Date dépassée","En cours")))
... B40: =IF(A40="","",YEAR(A40)&"-"&TEXT(MONTH(A40),"00")) | K40: =IF(I40="","",SUMIFS($R$8:$R$507,$Q$8:$Q$507,I40)) | L40: =IF(I40="","",MAX(0,J40-K40)) | M40: =IF(OR(I40="",N(J40)<=0),"",MIN(1,MAX(0,K40/J40))) | O40: =IF(I40="","",IF(K40>=J40,"Atteint ✓",IF(AND(N40<>"",N40<TODAY()),"Date dépassée","En cours")))
B41: =IF(A41="","",YEAR(A41)&"-"&TEXT(MONTH(A41),"00"))
B42: =IF(A42="","",YEAR(A42)&"-"&TEXT(MONTH(A42),"00"))
B43: =IF(A43="","",YEAR(A43)&"-"&TEXT(MONTH(A43),"00"))
B44: =IF(A44="","",YEAR(A44)&"-"&TEXT(MONTH(A44),"00"))
B45: =IF(A45="","",YEAR(A45)&"-"&TEXT(MONTH(A45),"00"))
B46: =IF(A46="","",YEAR(A46)&"-"&TEXT(MONTH(A46),"00"))
B47: =IF(A47="","",YEAR(A47)&"-"&TEXT(MONTH(A47),"00"))
B48: =IF(A48="","",YEAR(A48)&"-"&TEXT(MONTH(A48),"00"))
B49: =IF(A49="","",YEAR(A49)&"-"&TEXT(MONTH(A49),"00"))
B50: =IF(A50="","",YEAR(A50)&"-"&TEXT(MONTH(A50),"00"))
B51: =IF(A51="","",YEAR(A51)&"-"&TEXT(MONTH(A51),"00"))
B52: =IF(A52="","",YEAR(A52)&"-"&TEXT(MONTH(A52),"00"))
... B507: =IF(A507="","",YEAR(A507)&"-"&TEXT(MONTH(A507),"00"))

Sheet Mois
A1: Mois
A2: Une ligne par mois. Saisis le net reçu dès la paie : il remplace l’estimation.
A4: Mois | B4: Net reçu | C4: Jours entreprise | D4: Jours absence | E4: Épargne prévue | F4: Brut estimé | G4: Cotisations estimées | H4: Net estimé | I4: Net retenu | J4: Salaire | K4: Charges | L4: Charges payées | M4: Épargne versée | N4: Épargne retenue | O4: Dépenses | P4: Dépenses faites | Q4: Reste à vivre | R4: Statut
A5: 2026-09 | B5: 1400 | C5: 15 | D5: 0 | E5: 0 | F5: =IF($A5="","",MAX(0,Paramètres!$B$9+C5*(Paramètres!$B$10+Paramètres!$B$11)-D5*Paramètres!$B$14*Paramètres!$B$13)) -> 1547.35 | G5: =IF($A5="","",MAX(0,Paramètres!$B$15+Paramètres!$B$17*(F5-Paramètres!$B$16))) -> 208.38131 | H5: =IF($A5="","",MAX(0,ROUND(F5-G5+C5*Paramètres!$B$12,2))) -> 1494.97 | I5: =IF($A5="","",IF(B5="",H5,B5)) -> 1400 | J5: =IF($A5="","",IF(B5="","≈ estimé","reçu")) -> reçu | K5: =IF($A5="","",SUMIFS(Charges!$C$5:$C$504,Charges!$A$5:$A$504,A5)) -> 470 | L5: =IF($A5="","",SUMIFS(Charges!$C$5:$C$504,Charges!$A$5:$A$504,A5,Charges!$E$5:$E$504,"Oui")) -> 470 | M5: =IF($A5="","",SUMIFS(Épargne!$C$8:$C$507,Épargne!$B$8:$B$507,A5)) -> 0 | N5: =IF($A5="","",IF(A5<Paramètres!$B$4,M5,MAX(E5,M5))) -> 0 | O5: =IF($A5="","",SUMIFS(Dépenses!$B$5:$B$504,Dépenses!$E$5:$E$504,A5)) -> 95 | P5: =IF($A5="","",IF(A5>Paramètres!$B$4,0,SUMIFS(Dépenses!$B$5:$B$504,Dépenses!$E$5:$E$504,A5,Dépenses!$A$5:$A$504,"<="&TODAY()))) -> 95 | Q5: =IF($A5="","",I5-K5-N5-O5) -> 835 | R5: =IF($A5="","",IF(A5<Paramètres!$B$4,"terminé",IF(A5=Paramètres!$B$4,"en cours","à venir"))) -> terminé
A6: 2026-10 | C6: 15 | D6: 0 | E6: 0 | F6: =IF($A6="","",MAX(0,Paramètres!$B$9+C6*(Paramètres!$B$10+Paramètres!$B$11)-D6*Paramètres!$B$14*Paramètres!$B$13)) -> 1547.35 | G6: =IF($A6="","",MAX(0,Paramètres!$B$15+Paramètres!$B$17*(F6-Paramètres!$B$16))) -> 208.38131 | H6: =IF($A6="","",MAX(0,ROUND(F6-G6+C6*Paramètres!$B$12,2))) -> 1494.97 | I6: =IF($A6="","",IF(B6="",H6,B6)) -> 1494.97 | J6: =IF($A6="","",IF(B6="","≈ estimé","reçu")) -> ≈ estimé | K6: =IF($A6="","",SUMIFS(Charges!$C$5:$C$504,Charges!$A$5:$A$504,A6)) -> 470 | L6: =IF($A6="","",SUMIFS(Charges!$C$5:$C$504,Charges!$A$5:$A$504,A6,Charges!$E$5:$E$504,"Oui")) -> 450 | M6: =IF($A6="","",SUMIFS(Épargne!$C$8:$C$507,Épargne!$B$8:$B$507,A6)) -> 100 | N6: =IF($A6="","",IF(A6<Paramètres!$B$4,M6,MAX(E6,M6))) -> 100 | O6: =IF($A6="","",SUMIFS(Dépenses!$B$5:$B$504,Dépenses!$E$5:$E$504,A6)) -> 160 | P6: =IF($A6="","",IF(A6>Paramètres!$B$4,0,SUMIFS(Dépenses!$B$5:$B$504,Dépenses!$E$5:$E$504,A6,Dépenses!$A$5:$A$504,"<="&TODAY()))) -> 80 | Q6: =IF($A6="","",I6-K6-N6-O6) -> 764.97 | R6: =IF($A6="","",IF(A6<Paramètres!$B$4,"terminé",IF(A6=Paramètres!$B$4,"en cours","à venir"))) -> en cours
A7: 2026-11 | C7: 15 | D7: 0 | E7: 300 | F7: =IF($A7="","",MAX(0,Paramètres!$B$9+C7*(Paramètres!$B$10+Paramètres!$B$11)-D7*Paramètres!$B$14*Paramètres!$B$13)) -> 1547.35 | G7: =IF($A7="","",MAX(0,Paramètres!$B$15+Paramètres!$B$17*(F7-Paramètres!$B$16))) -> 208.38131 | H7: =IF($A7="","",MAX(0,ROUND(F7-G7+C7*Paramètres!$B$12,2))) -> 1494.97 | I7: =IF($A7="","",IF(B7="",H7,B7)) -> 1494.97 | J7: =IF($A7="","",IF(B7="","≈ estimé","reçu")) -> ≈ estimé | K7: =IF($A7="","",SUMIFS(Charges!$C$5:$C$504,Charges!$A$5:$A$504,A7)) -> 470 | L7: =IF($A7="","",SUMIFS(Charges!$C$5:$C$504,Charges!$A$5:$A$504,A7,Charges!$E$5:$E$504,"Oui")) -> 0 | M7: =IF($A7="","",SUMIFS(Épargne!$C$8:$C$507,Épargne!$B$8:$B$507,A7)) -> 0 | N7: =IF($A7="","",IF(A7<Paramètres!$B$4,M7,MAX(E7,M7))) -> 300 | O7: =IF($A7="","",SUMIFS(Dépenses!$B$5:$B$504,Dépenses!$E$5:$E$504,A7)) -> 0 | P7: =IF($A7="","",IF(A7>Paramètres!$B$4,0,SUMIFS(Dépenses!$B$5:$B$504,Dépenses!$E$5:$E$504,A7,Dépenses!$A$5:$A$504,"<="&TODAY()))) -> 0 | Q7: =IF($A7="","",I7-K7-N7-O7) -> 724.97 | R7: =IF($A7="","",IF(A7<Paramètres!$B$4,"terminé",IF(A7=Paramètres!$B$4,"en cours","à venir"))) -> à venir
A8: 2026-12 | C8: 15 | D8: 0 | E8: 0 | F8: =IF($A8="","",MAX(0,Paramètres!$B$9+C8*(Paramètres!$B$10+Paramètres!$B$11)-D8*Paramètres!$B$14*Paramètres!$B$13)) -> 1547.35 | G8: =IF($A8="","",MAX(0,Paramètres!$B$15+Paramètres!$B$17*(F8-Paramètres!$B$16))) -> 208.38131 | H8: =IF($A8="","",MAX(0,ROUND(F8-G8+C8*Paramètres!$B$12,2))) -> 1494.97 | I8: =IF($A8="","",IF(B8="",H8,B8)) -> 1494.97 | J8: =IF($A8="","",IF(B8="","≈ estimé","reçu")) -> ≈ estimé | K8: =IF($A8="","",SUMIFS(Charges!$C$5:$C$504,Charges!$A$5:$A$504,A8)) -> 470 | L8: =IF($A8="","",SUMIFS(Charges!$C$5:$C$504,Charges!$A$5:$A$504,A8,Charges!$E$5:$E$504,"Oui")) -> 0 | M8: =IF($A8="","",SUMIFS(Épargne!$C$8:$C$507,Épargne!$B$8:$B$507,A8)) -> 0 | N8: =IF($A8="","",IF(A8<Paramètres!$B$4,M8,MAX(E8,M8))) -> 0 | O8: =IF($A8="","",SUMIFS(Dépenses!$B$5:$B$504,Dépenses!$E$5:$E$504,A8)) -> 0 | P8: =IF($A8="","",IF(A8>Paramètres!$B$4,0,SUMIFS(Dépenses!$B$5:$B$504,Dépenses!$E$5:$E$504,A8,Dépenses!$A$5:$A$504,"<="&TODAY()))) -> 0 | Q8: =IF($A8="","",I8-K8-N8-O8) -> 1024.97 | R8: =IF($A8="","",IF(A8<Paramètres!$B$4,"terminé",IF(A8=Paramètres!$B$4,"en cours","à venir"))) -> à venir
A9: 2027-01 | C9: 15 | D9: 0 | E9: 300 | F9: =IF($A9="","",MAX(0,Paramètres!$B$9+C9*(Paramètres!$B$10+Paramètres!$B$11)-D9*Paramètres!$B$14*Paramètres!$B$13)) -> 1547.35 | G9: =IF($A9="","",MAX(0,Paramètres!$B$15+Paramètres!$B$17*(F9-Paramètres!$B$16))) -> 208.38131 | H9: =IF($A9="","",MAX(0,ROUND(F9-G9+C9*Paramètres!$B$12,2))) -> 1494.97 | I9: =IF($A9="","",IF(B9="",H9,B9)) -> 1494.97 | J9: =IF($A9="","",IF(B9="","≈ estimé","reçu")) -> ≈ estimé | K9: =IF($A9="","",SUMIFS(Charges!$C$5:$C$504,Charges!$A$5:$A$504,A9)) -> 470 | L9: =IF($A9="","",SUMIFS(Charges!$C$5:$C$504,Charges!$A$5:$A$504,A9,Charges!$E$5:$E$504,"Oui")) -> 0 | M9: =IF($A9="","",SUMIFS(Épargne!$C$8:$C$507,Épargne!$B$8:$B$507,A9)) -> 0 | N9: =IF($A9="","",IF(A9<Paramètres!$B$4,M9,MAX(E9,M9))) -> 300 | O9: =IF($A9="","",SUMIFS(Dépenses!$B$5:$B$504,Dépenses!$E$5:$E$504,A9)) -> 0 | P9: =IF($A9="","",IF(A9>Paramètres!$B$4,0,SUMIFS(Dépenses!$B$5:$B$504,Dépenses!$E$5:$E$504,A9,Dépenses!$A$5:$A$504,"<="&TODAY()))) -> 0 | Q9: =IF($A9="","",I9-K9-N9-O9) -> 724.97 | R9: =IF($A9="","",IF(A9<Paramètres!$B$4,"terminé",IF(A9=Paramètres!$B$4,"en cours","à venir"))) -> à venir
A10: 2027-02 | C10: 15 | D10: 0 | E10: 300 | F10: =IF($A10="","",MAX(0,Paramètres!$B$9+C10*(Paramètres!$B$10+Paramètres!$B$11)-D10*Paramètres!$B$14*Paramètres!$B$13)) -> 1547.35 | G10: =IF($A10="","",MAX(0,Paramètres!$B$15+Paramètres!$B$17*(F10-Paramètres!$B$16))) -> 208.38131 | H10: =IF($A10="","",MAX(0,ROUND(F10-G10+C10*Paramètres!$B$12,2))) -> 1494.97 | I10: =IF($A10="","",IF(B10="",H10,B10)) -> 1494.97 | J10: =IF($A10="","",IF(B10="","≈ estimé","reçu")) -> ≈ estimé | K10: =IF($A10="","",SUMIFS(Charges!$C$5:$C$504,Charges!$A$5:$A$504,A10)) -> 470 | L10: =IF($A10="","",SUMIFS(Charges!$C$5:$C$504,Charges!$A$5:$A$504,A10,Charges!$E$5:$E$504,"Oui")) -> 0 | M10: =IF($A10="","",SUMIFS(Épargne!$C$8:$C$507,Épargne!$B$8:$B$507,A10)) -> 0 | N10: =IF($A10="","",IF(A10<Paramètres!$B$4,M10,MAX(E10,M10))) -> 300 | O10: =IF($A10="","",SUMIFS(Dépenses!$B$5:$B$504,Dépenses!$E$5:$E$504,A10)) -> 0 | P10: =IF($A10="","",IF(A10>Paramètres!$B$4,0,SUMIFS(Dépenses!$B$5:$B$504,Dépenses!$E$5:$E$504,A10,Dépenses!$A$5:$A$504,"<="&TODAY()))) -> 0 | Q10: =IF($A10="","",I10-K10-N10-O10) -> 724.97 | R10: =IF($A10="","",IF(A10<Paramètres!$B$4,"terminé",IF(A10=Paramètres!$B$4,"en cours","à venir"))) -> à venir
F11: =IF($A11="","",MAX(0,Paramètres!$B$9+C11*(Paramètres!$B$10+Paramètres!$B$11)-D11*Paramètres!$B$14*Paramètres!$B$13)) | G11: =IF($A11="","",MAX(0,Paramètres!$B$15+Paramètres!$B$17*(F11-Paramètres!$B$16))) | H11: =IF($A11="","",MAX(0,ROUND(F11-G11+C11*Paramètres!$B$12,2))) | I11: =IF($A11="","",IF(B11="",H11,B11)) | J11: =IF($A11="","",IF(B11="","≈ estimé","reçu")) | K11: =IF($A11="","",SUMIFS(Charges!$C$5:$C$504,Charges!$A$5:$A$504,A11)) | L11: =IF($A11="","",SUMIFS(Charges!$C$5:$C$504,Charges!$A$5:$A$504,A11,Charges!$E$5:$E$504,"Oui")) | M11: =IF($A11="","",SUMIFS(Épargne!$C$8:$C$507,Épargne!$B$8:$B$507,A11)) | N11: =IF($A11="","",IF(A11<Paramètres!$B$4,M11,MAX(E11,M11))) | O11: =IF($A11="","",SUMIFS(Dépenses!$B$5:$B$504,Dépenses!$E$5:$E$504,A11)) | P11: =IF($A11="","",IF(A11>Paramètres!$B$4,0,SUMIFS(Dépenses!$B$5:$B$504,Dépenses!$E$5:$E$504,A11,Dépenses!$A$5:$A$504,"<="&TODAY()))) | Q11: =IF($A11="","",I11-K11-N11-O11) | R11: =IF($A11="","",IF(A11<Paramètres!$B$4,"terminé",IF(A11=Paramètres!$B$4,"en cours","à venir")))
F12: =IF($A12="","",MAX(0,Paramètres!$B$9+C12*(Paramètres!$B$10+Paramètres!$B$11)-D12*Paramètres!$B$14*Paramètres!$B$13)) | G12: =IF($A12="","",MAX(0,Paramètres!$B$15+Paramètres!$B$17*(F12-Paramètres!$B$16))) | H12: =IF($A12="","",MAX(0,ROUND(F12-G12+C12*Paramètres!$B$12,2))) | I12: =IF($A12="","",IF(B12="",H12,B12)) | J12: =IF($A12="","",IF(B12="","≈ estimé","reçu")) | K12: =IF($A12="","",SUMIFS(Charges!$C$5:$C$504,Charges!$A$5:$A$504,A12)) | L12: =IF($A12="","",SUMIFS(Charges!$C$5:$C$504,Charges!$A$5:$A$504,A12,Charges!$E$5:$E$504,"Oui")) | M12: =IF($A12="","",SUMIFS(Épargne!$C$8:$C$507,Épargne!$B$8:$B$507,A12)) | N12: =IF($A12="","",IF(A12<Paramètres!$B$4,M12,MAX(E12,M12))) | O12: =IF($A12="","",SUMIFS(Dépenses!$B$5:$B$504,Dépenses!$E$5:$E$504,A12)) | P12: =IF($A12="","",IF(A12>Paramètres!$B$4,0,SUMIFS(Dépenses!$B$5:$B$504,Dépenses!$E$5:$E$504,A12,Dépenses!$A$5:$A$504,"<="&TODAY()))) | Q12: =IF($A12="","",I12-K12-N12-O12) | R12: =IF($A12="","",IF(A12<Paramètres!$B$4,"terminé",IF(A12=Paramètres!$B$4,"en cours","à venir")))
F13: =IF($A13="","",MAX(0,Paramètres!$B$9+C13*(Paramètres!$B$10+Paramètres!$B$11)-D13*Paramètres!$B$14*Paramètres!$B$13)) | G13: =IF($A13="","",MAX(0,Paramètres!$B$15+Paramètres!$B$17*(F13-Paramètres!$B$16))) | H13: =IF($A13="","",MAX(0,ROUND(F13-G13+C13*Paramètres!$B$12,2))) | I13: =IF($A13="","",IF(B13="",H13,B13)) | J13: =IF($A13="","",IF(B13="","≈ estimé","reçu")) | K13: =IF($A13="","",SUMIFS(Charges!$C$5:$C$504,Charges!$A$5:$A$504,A13)) | L13: =IF($A13="","",SUMIFS(Charges!$C$5:$C$504,Charges!$A$5:$A$504,A13,Charges!$E$5:$E$504,"Oui")) | M13: =IF($A13="","",SUMIFS(Épargne!$C$8:$C$507,Épargne!$B$8:$B$507,A13)) | N13: =IF($A13="","",IF(A13<Paramètres!$B$4,M13,MAX(E13,M13))) | O13: =IF($A13="","",SUMIFS(Dépenses!$B$5:$B$504,Dépenses!$E$5:$E$504,A13)) | P13: =IF($A13="","",IF(A13>Paramètres!$B$4,0,SUMIFS(Dépenses!$B$5:$B$504,Dépenses!$E$5:$E$504,A13,Dépenses!$A$5:$A$504,"<="&TODAY()))) | Q13: =IF($A13="","",I13-K13-N13-O13) | R13: =IF($A13="","",IF(A13<Paramètres!$B$4,"terminé",IF(A13=Paramètres!$B$4,"en cours","à venir")))
F14: =IF($A14="","",MAX(0,Paramètres!$B$9+C14*(Paramètres!$B$10+Paramètres!$B$11)-D14*Paramètres!$B$14*Paramètres!$B$13)) | G14: =IF($A14="","",MAX(0,Paramètres!$B$15+Paramètres!$B$17*(F14-Paramètres!$B$16))) | H14: =IF($A14="","",MAX(0,ROUND(F14-G14+C14*Paramètres!$B$12,2))) | I14: =IF($A14="","",IF(B14="",H14,B14)) | J14: =IF($A14="","",IF(B14="","≈ estimé","reçu")) | K14: =IF($A14="","",SUMIFS(Charges!$C$5:$C$504,Charges!$A$5:$A$504,A14)) | L14: =IF($A14="","",SUMIFS(Charges!$C$5:$C$504,Charges!$A$5:$A$504,A14,Charges!$E$5:$E$504,"Oui")) | M14: =IF($A14="","",SUMIFS(Épargne!$C$8:$C$507,Épargne!$B$8:$B$507,A14)) | N14: =IF($A14="","",IF(A14<Paramètres!$B$4,M14,MAX(E14,M14))) | O14: =IF($A14="","",SUMIFS(Dépenses!$B$5:$B$504,Dépenses!$E$5:$E$504,A14)) | P14: =IF($A14="","",IF(A14>Paramètres!$B$4,0,SUMIFS(Dépenses!$B$5:$B$504,Dépenses!$E$5:$E$504,A14,Dépenses!$A$5:$A$504,"<="&TODAY()))) | Q14: =IF($A14="","",I14-K14-N14-O14) | R14: =IF($A14="","",IF(A14<Paramètres!$B$4,"terminé",IF(A14=Paramètres!$B$4,"en cours","à venir")))
F15: =IF($A15="","",MAX(0,Paramètres!$B$9+C15*(Paramètres!$B$10+Paramètres!$B$11)-D15*Paramètres!$B$14*Paramètres!$B$13)) | G15: =IF($A15="","",MAX(0,Paramètres!$B$15+Paramètres!$B$17*(F15-Paramètres!$B$16))) | H15: =IF($A15="","",MAX(0,ROUND(F15-G15+C15*Paramètres!$B$12,2))) | I15: =IF($A15="","",IF(B15="",H15,B15)) | J15: =IF($A15="","",IF(B15="","≈ estimé","reçu")) | K15: =IF($A15="","",SUMIFS(Charges!$C$5:$C$504,Charges!$A$5:$A$504,A15)) | L15: =IF($A15="","",SUMIFS(Charges!$C$5:$C$504,Charges!$A$5:$A$504,A15,Charges!$E$5:$E$504,"Oui")) | M15: =IF($A15="","",SUMIFS(Épargne!$C$8:$C$507,Épargne!$B$8:$B$507,A15)) | N15: =IF($A15="","",IF(A15<Paramètres!$B$4,M15,MAX(E15,M15))) | O15: =IF($A15="","",SUMIFS(Dépenses!$B$5:$B$504,Dépenses!$E$5:$E$504,A15)) | P15: =IF($A15="","",IF(A15>Paramètres!$B$4,0,SUMIFS(Dépenses!$B$5:$B$504,Dépenses!$E$5:$E$504,A15,Dépenses!$A$5:$A$504,"<="&TODAY()))) | Q15: =IF($A15="","",I15-K15-N15-O15) | R15: =IF($A15="","",IF(A15<Paramètres!$B$4,"terminé",IF(A15=Paramètres!$B$4,"en cours","à venir")))
F16: =IF($A16="","",MAX(0,Paramètres!$B$9+C16*(Paramètres!$B$10+Paramètres!$B$11)-D16*Paramètres!$B$14*Paramètres!$B$13)) | G16: =IF($A16="","",MAX(0,Paramètres!$B$15+Paramètres!$B$17*(F16-Paramètres!$B$16))) | H16: =IF($A16="","",MAX(0,ROUND(F16-G16+C16*Paramètres!$B$12,2))) | I16: =IF($A16="","",IF(B16="",H16,B16)) | J16: =IF($A16="","",IF(B16="","≈ estimé","reçu")) | K16: =IF($A16="","",SUMIFS(Charges!$C$5:$C$504,Charges!$A$5:$A$504,A16)) | L16: =IF($A16="","",SUMIFS(Charges!$C$5:$C$504,Charges!$A$5:$A$504,A16,Charges!$E$5:$E$504,"Oui")) | M16: =IF($A16="","",SUMIFS(Épargne!$C$8:$C$507,Épargne!$B$8:$B$507,A16)) | N16: =IF($A16="","",IF(A16<Paramètres!$B$4,M16,MAX(E16,M16))) | O16: =IF($A16="","",SUMIFS(Dépenses!$B$5:$B$504,Dépenses!$E$5:$E$504,A16)) | P16: =IF($A16="","",IF(A16>Paramètres!$B$4,0,SUMIFS(Dépenses!$B$5:$B$504,Dépenses!$E$5:$E$504,A16,Dépenses!$A$5:$A$504,"<="&TODAY()))) | Q16: =IF($A16="","",I16-K16-N16-O16) | R16: =IF($A16="","",IF(A16<Paramètres!$B$4,"terminé",IF(A16=Paramètres!$B$4,"en cours","à venir")))
F17: =IF($A17="","",MAX(0,Paramètres!$B$9+C17*(Paramètres!$B$10+Paramètres!$B$11)-D17*Paramètres!$B$14*Paramètres!$B$13)) | G17: =IF($A17="","",MAX(0,Paramètres!$B$15+Paramètres!$B$17*(F17-Paramètres!$B$16))) | H17: =IF($A17="","",MAX(0,ROUND(F17-G17+C17*Paramètres!$B$12,2))) | I17: =IF($A17="","",IF(B17="",H17,B17)) | J17: =IF($A17="","",IF(B17="","≈ estimé","reçu")) | K17: =IF($A17="","",SUMIFS(Charges!$C$5:$C$504,Charges!$A$5:$A$504,A17)) | L17: =IF($A17="","",SUMIFS(Charges!$C$5:$C$504,Charges!$A$5:$A$504,A17,Charges!$E$5:$E$504,"Oui")) | M17: =IF($A17="","",SUMIFS(Épargne!$C$8:$C$507,Épargne!$B$8:$B$507,A17)) | N17: =IF($A17="","",IF(A17<Paramètres!$B$4,M17,MAX(E17,M17))) | O17: =IF($A17="","",SUMIFS(Dépenses!$B$5:$B$504,Dépenses!$E$5:$E$504,A17)) | P17: =IF($A17="","",IF(A17>Paramètres!$B$4,0,SUMIFS(Dépenses!$B$5:$B$504,Dépenses!$E$5:$E$504,A17,Dépenses!$A$5:$A$504,"<="&TODAY()))) | Q17: =IF($A17="","",I17-K17-N17-O17) | R17: =IF($A17="","",IF(A17<Paramètres!$B$4,"terminé",IF(A17=Paramètres!$B$4,"en cours","à venir")))
F18: =IF($A18="","",MAX(0,Paramètres!$B$9+C18*(Paramètres!$B$10+Paramètres!$B$11)-D18*Paramètres!$B$14*Paramètres!$B$13)) | G18: =IF($A18="","",MAX(0,Paramètres!$B$15+Paramètres!$B$17*(F18-Paramètres!$B$16))) | H18: =IF($A18="","",MAX(0,ROUND(F18-G18+C18*Paramètres!$B$12,2))) | I18: =IF($A18="","",IF(B18="",H18,B18)) | J18: =IF($A18="","",IF(B18="","≈ estimé","reçu")) | K18: =IF($A18="","",SUMIFS(Charges!$C$5:$C$504,Charges!$A$5:$A$504,A18)) | L18: =IF($A18="","",SUMIFS(Charges!$C$5:$C$504,Charges!$A$5:$A$504,A18,Charges!$E$5:$E$504,"Oui")) | M18: =IF($A18="","",SUMIFS(Épargne!$C$8:$C$507,Épargne!$B$8:$B$507,A18)) | N18: =IF($A18="","",IF(A18<Paramètres!$B$4,M18,MAX(E18,M18))) | O18: =IF($A18="","",SUMIFS(Dépenses!$B$5:$B$504,Dépenses!$E$5:$E$504,A18)) | P18: =IF($A18="","",IF(A18>Paramètres!$B$4,0,SUMIFS(Dépenses!$B$5:$B$504,Dépenses!$E$5:$E$504,A18,Dépenses!$A$5:$A$504,"<="&TODAY()))) | Q18: =IF($A18="","",I18-K18-N18-O18) | R18: =IF($A18="","",IF(A18<Paramètres!$B$4,"terminé",IF(A18=Paramètres!$B$4,"en cours","à venir")))
F19: =IF($A19="","",MAX(0,Paramètres!$B$9+C19*(Paramètres!$B$10+Paramètres!$B$11)-D19*Paramètres!$B$14*Paramètres!$B$13)) | G19: =IF($A19="","",MAX(0,Paramètres!$B$15+Paramètres!$B$17*(F19-Paramètres!$B$16))) | H19: =IF($A19="","",MAX(0,ROUND(F19-G19+C19*Paramètres!$B$12,2))) | I19: =IF($A19="","",IF(B19="",H19,B19)) | J19: =IF($A19="","",IF(B19="","≈ estimé","reçu")) | K19: =IF($A19="","",SUMIFS(Charges!$C$5:$C$504,Charges!$A$5:$A$504,A19)) | L19: =IF($A19="","",SUMIFS(Charges!$C$5:$C$504,Charges!$A$5:$A$504,A19,Charges!$E$5:$E$504,"Oui")) | M19: =IF($A19="","",SUMIFS(Épargne!$C$8:$C$507,Épargne!$B$8:$B$507,A19)) | N19: =IF($A19="","",IF(A19<Paramètres!$B$4,M19,MAX(E19,M19))) | O19: =IF($A19="","",SUMIFS(Dépenses!$B$5:$B$504,Dépenses!$E$5:$E$504,A19)) | P19: =IF($A19="","",IF(A19>Paramètres!$B$4,0,SUMIFS(Dépenses!$B$5:$B$504,Dépenses!$E$5:$E$504,A19,Dépenses!$A$5:$A$504,"<="&TODAY()))) | Q19: =IF($A19="","",I19-K19-N19-O19) | R19: =IF($A19="","",IF(A19<Paramètres!$B$4,"terminé",IF(A19=Paramètres!$B$4,"en cours","à venir")))
F20: =IF($A20="","",MAX(0,Paramètres!$B$9+C20*(Paramètres!$B$10+Paramètres!$B$11)-D20*Paramètres!$B$14*Paramètres!$B$13)) | G20: =IF($A20="","",MAX(0,Paramètres!$B$15+Paramètres!$B$17*(F20-Paramètres!$B$16))) | H20: =IF($A20="","",MAX(0,ROUND(F20-G20+C20*Paramètres!$B$12,2))) | I20: =IF($A20="","",IF(B20="",H20,B20)) | J20: =IF($A20="","",IF(B20="","≈ estimé","reçu")) | K20: =IF($A20="","",SUMIFS(Charges!$C$5:$C$504,Charges!$A$5:$A$504,A20)) | L20: =IF($A20="","",SUMIFS(Charges!$C$5:$C$504,Charges!$A$5:$A$504,A20,Charges!$E$5:$E$504,"Oui")) | M20: =IF($A20="","",SUMIFS(Épargne!$C$8:$C$507,Épargne!$B$8:$B$507,A20)) | N20: =IF($A20="","",IF(A20<Paramètres!$B$4,M20,MAX(E20,M20))) | O20: =IF($A20="","",SUMIFS(Dépenses!$B$5:$B$504,Dépenses!$E$5:$E$504,A20)) | P20: =IF($A20="","",IF(A20>Paramètres!$B$4,0,SUMIFS(Dépenses!$B$5:$B$504,Dépenses!$E$5:$E$504,A20,Dépenses!$A$5:$A$504,"<="&TODAY()))) | Q20: =IF($A20="","",I20-K20-N20-O20) | R20: =IF($A20="","",IF(A20<Paramètres!$B$4,"terminé",IF(A20=Paramètres!$B$4,"en cours","à venir")))
F21: =IF($A21="","",MAX(0,Paramètres!$B$9+C21*(Paramètres!$B$10+Paramètres!$B$11)-D21*Paramètres!$B$14*Paramètres!$B$13)) | G21: =IF($A21="","",MAX(0,Paramètres!$B$15+Paramètres!$B$17*(F21-Paramètres!$B$16))) | H21: =IF($A21="","",MAX(0,ROUND(F21-G21+C21*Paramètres!$B$12,2))) | I21: =IF($A21="","",IF(B21="",H21,B21)) | J21: =IF($A21="","",IF(B21="","≈ estimé","reçu")) | K21: =IF($A21="","",SUMIFS(Charges!$C$5:$C$504,Charges!$A$5:$A$504,A21)) | L21: =IF($A21="","",SUMIFS(Charges!$C$5:$C$504,Charges!$A$5:$A$504,A21,Charges!$E$5:$E$504,"Oui")) | M21: =IF($A21="","",SUMIFS(Épargne!$C$8:$C$507,Épargne!$B$8:$B$507,A21)) | N21: =IF($A21="","",IF(A21<Paramètres!$B$4,M21,MAX(E21,M21))) | O21: =IF($A21="","",SUMIFS(Dépenses!$B$5:$B$504,Dépenses!$E$5:$E$504,A21)) | P21: =IF($A21="","",IF(A21>Paramètres!$B$4,0,SUMIFS(Dépenses!$B$5:$B$504,Dépenses!$E$5:$E$504,A21,Dépenses!$A$5:$A$504,"<="&TODAY()))) | Q21: =IF($A21="","",I21-K21-N21-O21) | R21: =IF($A21="","",IF(A21<Paramètres!$B$4,"terminé",IF(A21=Paramètres!$B$4,"en cours","à venir")))
F22: =IF($A22="","",MAX(0,Paramètres!$B$9+C22*(Paramètres!$B$10+Paramètres!$B$11)-D22*Paramètres!$B$14*Paramètres!$B$13)) | G22: =IF($A22="","",MAX(0,Paramètres!$B$15+Paramètres!$B$17*(F22-Paramètres!$B$16))) | H22: =IF($A22="","",MAX(0,ROUND(F22-G22+C22*Paramètres!$B$12,2))) | I22: =IF($A22="","",IF(B22="",H22,B22)) | J22: =IF($A22="","",IF(B22="","≈ estimé","reçu")) | K22: =IF($A22="","",SUMIFS(Charges!$C$5:$C$504,Charges!$A$5:$A$504,A22)) | L22: =IF($A22="","",SUMIFS(Charges!$C$5:$C$504,Charges!$A$5:$A$504,A22,Charges!$E$5:$E$504,"Oui")) | M22: =IF($A22="","",SUMIFS(Épargne!$C$8:$C$507,Épargne!$B$8:$B$507,A22)) | N22: =IF($A22="","",IF(A22<Paramètres!$B$4,M22,MAX(E22,M22))) | O22: =IF($A22="","",SUMIFS(Dépenses!$B$5:$B$504,Dépenses!$E$5:$E$504,A22)) | P22: =IF($A22="","",IF(A22>Paramètres!$B$4,0,SUMIFS(Dépenses!$B$5:$B$504,Dépenses!$E$5:$E$504,A22,Dépenses!$A$5:$A$504,"<="&TODAY()))) | Q22: =IF($A22="","",I22-K22-N22-O22) | R22: =IF($A22="","",IF(A22<Paramètres!$B$4,"terminé",IF(A22=Paramètres!$B$4,"en cours","à venir")))
... F40: =IF($A40="","",MAX(0,Paramètres!$B$9+C40*(Paramètres!$B$10+Paramètres!$B$11)-D40*Paramètres!$B$14*Paramètres!$B$13)) | G40: =IF($A40="","",MAX(0,Paramètres!$B$15+Paramètres!$B$17*(F40-Paramètres!$B$16))) | H40: =IF($A40="","",MAX(0,ROUND(F40-G40+C40*Paramètres!$B$12,2))) | I40: =IF($A40="","",IF(B40="",H40,B40)) | J40: =IF($A40="","",IF(B40="","≈ estimé","reçu")) | K40: =IF($A40="","",SUMIFS(Charges!$C$5:$C$504,Charges!$A$5:$A$504,A40)) | L40: =IF($A40="","",SUMIFS(Charges!$C$5:$C$504,Charges!$A$5:$A$504,A40,Charges!$E$5:$E$504,"Oui")) | M40: =IF($A40="","",SUMIFS(Épargne!$C$8:$C$507,Épargne!$B$8:$B$507,A40)) | N40: =IF($A40="","",IF(A40<Paramètres!$B$4,M40,MAX(E40,M40))) | O40: =IF($A40="","",SUMIFS(Dépenses!$B$5:$B$504,Dépenses!$E$5:$E$504,A40)) | P40: =IF($A40="","",IF(A40>Paramètres!$B$4,0,SUMIFS(Dépenses!$B$5:$B$504,Dépenses!$E$5:$E$504,A40,Dépenses!$A$5:$A$504,"<="&TODAY()))) | Q40: =IF($A40="","",I40-K40-N40-O40) | R40: =IF($A40="","",IF(A40<Paramètres!$B$4,"terminé",IF(A40=Paramètres!$B$4,"en cours","à venir")))

Sheet Comparer
A1: Comparer deux mois
A2: Écart = B − A. Une baisse des dépenses n’est pas forcément une amélioration (mois incomplet, oubli de saisie…).
A4: Mois A | B4: 2026-09 | C4: =IFERROR(INDEX(Mois!$R$5:$R$40,MATCH(B4,Mois!$A$5:$A$40,0))&" · salaire "&INDEX(Mois!$J$5:$J$40,MATCH(B4,Mois!$A$5:$A$40,0)),"") -> terminé · salaire reçu
A5: Mois B | B5: 2026-10 | C5: =IFERROR(INDEX(Mois!$R$5:$R$40,MATCH(B5,Mois!$A$5:$A$40,0))&" · salaire "&INDEX(Mois!$J$5:$J$40,MATCH(B5,Mois!$A$5:$A$40,0)),"") -> en cours · salaire ≈ estimé
B7: A | C7: B | D7: Écart (B − A) | E7: Variation
A8: Salaire | B8: =IFERROR(INDEX(Mois!$I$5:$I$40,MATCH($B$4,Mois!$A$5:$A$40,0)),0) -> 1400 | C8: =IFERROR(INDEX(Mois!$I$5:$I$40,MATCH($B$5,Mois!$A$5:$A$40,0)),0) -> 1494.97 | D8: =C8-B8 -> 94.97 | E8: =IF(B8>=1,(C8-B8)/B8,"—") -> 0.067835714
A9: Charges fixes | B9: =IFERROR(INDEX(Mois!$K$5:$K$40,MATCH($B$4,Mois!$A$5:$A$40,0)),0) -> 470 | C9: =IFERROR(INDEX(Mois!$K$5:$K$40,MATCH($B$5,Mois!$A$5:$A$40,0)),0) -> 470 | D9: =C9-B9 -> 0 | E9: =IF(B9>=1,(C9-B9)/B9,"—") -> 0
A10: Dépenses | B10: =IFERROR(INDEX(Mois!$O$5:$O$40,MATCH($B$4,Mois!$A$5:$A$40,0)),0) -> 95 | C10: =IFERROR(INDEX(Mois!$O$5:$O$40,MATCH($B$5,Mois!$A$5:$A$40,0)),0) -> 160 | D10: =C10-B10 -> 65 | E10: =IF(B10>=1,(C10-B10)/B10,"—") -> 0.68421053
A11: Épargne versée | B11: =IFERROR(INDEX(Mois!$M$5:$M$40,MATCH($B$4,Mois!$A$5:$A$40,0)),0) -> 0 | C11: =IFERROR(INDEX(Mois!$M$5:$M$40,MATCH($B$5,Mois!$A$5:$A$40,0)),0) -> 100 | D11: =C11-B11 -> 100 | E11: =IF(B11>=1,(C11-B11)/B11,"—") -> —
A12: Reste à vivre | B12: =IFERROR(INDEX(Mois!$Q$5:$Q$40,MATCH($B$4,Mois!$A$5:$A$40,0)),0) -> 835 | C12: =IFERROR(INDEX(Mois!$Q$5:$Q$40,MATCH($B$5,Mois!$A$5:$A$40,0)),0) -> 764.97 | D12: =C12-B12 -> -70.03 | E12: =IF(B12>=1,(C12-B12)/B12,"—") -> -0.083868263
A14: Dépenses par catégorie
A15: =IF(Paramètres!A22="","",Paramètres!A22) -> Transport | B15: =IF($A15="","",SUMIFS(Dépenses!$B$5:$B$504,Dépenses!$E$5:$E$504,$B$4,Dépenses!$C$5:$C$504,$A15)) -> 35 | C15: =IF($A15="","",SUMIFS(Dépenses!$B$5:$B$504,Dépenses!$E$5:$E$504,$B$5,Dépenses!$C$5:$C$504,$A15)) -> 0 | D15: =IF($A15="","",C15-B15) -> -35 | E15: =IF($A15="","",IF(B15>=1,(C15-B15)/B15,"—")) -> -1
A16: =IF(Paramètres!A23="","",Paramètres!A23) -> Courses | B16: =IF($A16="","",SUMIFS(Dépenses!$B$5:$B$504,Dépenses!$E$5:$E$504,$B$4,Dépenses!$C$5:$C$504,$A16)) -> 40 | C16: =IF($A16="","",SUMIFS(Dépenses!$B$5:$B$504,Dépenses!$E$5:$E$504,$B$5,Dépenses!$C$5:$C$504,$A16)) -> 50 | D16: =IF($A16="","",C16-B16) -> 10 | E16: =IF($A16="","",IF(B16>=1,(C16-B16)/B16,"—")) -> 0.25
A17: =IF(Paramètres!A24="","",Paramètres!A24) -> Restaurants | B17: =IF($A17="","",SUMIFS(Dépenses!$B$5:$B$504,Dépenses!$E$5:$E$504,$B$4,Dépenses!$C$5:$C$504,$A17)) -> 20 | C17: =IF($A17="","",SUMIFS(Dépenses!$B$5:$B$504,Dépenses!$E$5:$E$504,$B$5,Dépenses!$C$5:$C$504,$A17)) -> 30 | D17: =IF($A17="","",C17-B17) -> 10 | E17: =IF($A17="","",IF(B17>=1,(C17-B17)/B17,"—")) -> 0.5
A18: =IF(Paramètres!A25="","",Paramètres!A25) -> Divertissement | B18: =IF($A18="","",SUMIFS(Dépenses!$B$5:$B$504,Dépenses!$E$5:$E$504,$B$4,Dépenses!$C$5:$C$504,$A18)) -> 0 | C18: =IF($A18="","",SUMIFS(Dépenses!$B$5:$B$504,Dépenses!$E$5:$E$504,$B$5,Dépenses!$C$5:$C$504,$A18)) -> 0 | D18: =IF($A18="","",C18-B18) -> 0 | E18: =IF($A18="","",IF(B18>=1,(C18-B18)/B18,"—")) -> —
A19: =IF(Paramètres!A26="","",Paramètres!A26) -> Achats | B19: =IF($A19="","",SUMIFS(Dépenses!$B$5:$B$504,Dépenses!$E$5:$E$504,$B$4,Dépenses!$C$5:$C$504,$A19)) -> 0 | C19: =IF($A19="","",SUMIFS(Dépenses!$B$5:$B$504,Dépenses!$E$5:$E$504,$B$5,Dépenses!$C$5:$C$504,$A19)) -> 80 | D19: =IF($A19="","",C19-B19) -> 80 | E19: =IF($A19="","",IF(B19>=1,(C19-B19)/B19,"—")) -> —
A20: =IF(Paramètres!A27="","",Paramètres!A27) -> Argent de poche | B20: =IF($A20="","",SUMIFS(Dépenses!$B$5:$B$504,Dépenses!$E$5:$E$504,$B$4,Dépenses!$C$5:$C$504,$A20)) -> 0 | C20: =IF($A20="","",SUMIFS(Dépenses!$B$5:$B$504,Dépenses!$E$5:$E$504,$B$5,Dépenses!$C$5:$C$504,$A20)) -> 0 | D20: =IF($A20="","",C20-B20) -> 0 | E20: =IF($A20="","",IF(B20>=1,(C20-B20)/B20,"—")) -> —
A21: =IF(Paramètres!A28="","",Paramètres!A28) -> Santé | B21: =IF($A21="","",SUMIFS(Dépenses!$B$5:$B$504,Dépenses!$E$5:$E$504,$B$4,Dépenses!$C$5:$C$504,$A21)) -> 0 | C21: =IF($A21="","",SUMIFS(Dépenses!$B$5:$B$504,Dépenses!$E$5:$E$504,$B$5,Dépenses!$C$5:$C$504,$A21)) -> 0 | D21: =IF($A21="","",C21-B21) -> 0 | E21: =IF($A21="","",IF(B21>=1,(C21-B21)/B21,"—")) -> —
A22: =IF(Paramètres!A29="","",Paramètres!A29) -> Général | B22: =IF($A22="","",SUMIFS(Dépenses!$B$5:$B$504,Dépenses!$E$5:$E$504,$B$4,Dépenses!$C$5:$C$504,$A22)) -> 0 | C22: =IF($A22="","",SUMIFS(Dépenses!$B$5:$B$504,Dépenses!$E$5:$E$504,$B$5,Dépenses!$C$5:$C$504,$A22)) -> 0 | D22: =IF($A22="","",C22-B22) -> 0 | E22: =IF($A22="","",IF(B22>=1,(C22-B22)/B22,"—")) -> —
A23: =IF(Paramètres!A30="","",Paramètres!A30) | B23: =IF($A23="","",SUMIFS(Dépenses!$B$5:$B$504,Dépenses!$E$5:$E$504,$B$4,Dépenses!$C$5:$C$504,$A23)) | C23: =IF($A23="","",SUMIFS(Dépenses!$B$5:$B$504,Dépenses!$E$5:$E$504,$B$5,Dépenses!$C$5:$C$504,$A23)) | D23: =IF($A23="","",C23-B23) | E23: =IF($A23="","",IF(B23>=1,(C23-B23)/B23,"—"))
A24: =IF(Paramètres!A31="","",Paramètres!A31) | B24: =IF($A24="","",SUMIFS(Dépenses!$B$5:$B$504,Dépenses!$E$5:$E$504,$B$4,Dépenses!$C$5:$C$504,$A24)) | C24: =IF($A24="","",SUMIFS(Dépenses!$B$5:$B$504,Dépenses!$E$5:$E$504,$B$5,Dépenses!$C$5:$C$504,$A24)) | D24: =IF($A24="","",C24-B24) | E24: =IF($A24="","",IF(B24>=1,(C24-B24)/B24,"—"))
A25: =IF(Paramètres!A32="","",Paramètres!A32) | B25: =IF($A25="","",SUMIFS(Dépenses!$B$5:$B$504,Dépenses!$E$5:$E$504,$B$4,Dépenses!$C$5:$C$504,$A25)) | C25: =IF($A25="","",SUMIFS(Dépenses!$B$5:$B$504,Dépenses!$E$5:$E$504,$B$5,Dépenses!$C$5:$C$504,$A25)) | D25: =IF($A25="","",C25-B25) | E25: =IF($A25="","",IF(B25>=1,(C25-B25)/B25,"—"))
A26: =IF(Paramètres!A33="","",Paramètres!A33) | B26: =IF($A26="","",SUMIFS(Dépenses!$B$5:$B$504,Dépenses!$E$5:$E$504,$B$4,Dépenses!$C$5:$C$504,$A26)) | C26: =IF($A26="","",SUMIFS(Dépenses!$B$5:$B$504,Dépenses!$E$5:$E$504,$B$5,Dépenses!$C$5:$C$504,$A26)) | D26: =IF($A26="","",C26-B26) | E26: =IF($A26="","",IF(B26>=1,(C26-B26)/B26,"—"))
... A30: =IF(Paramètres!A37="","",Paramètres!A37) | B30: =IF($A30="","",SUMIFS(Dépenses!$B$5:$B$504,Dépenses!$E$5:$E$504,$B$4,Dépenses!$C$5:$C$504,$A30)) | C30: =IF($A30="","",SUMIFS(Dépenses!$B$5:$B$504,Dépenses!$E$5:$E$504,$B$5,Dépenses!$C$5:$C$504,$A30)) | D30: =IF($A30="","",C30-B30) | E30: =IF($A30="","",IF(B30>=1,(C30-B30)/B30,"—"))

Sheet Mode d’emploi
A1: Mode d’emploi
A2: Les chiffres déjà présents sont des exemples : remplace-les par les tiens.
A4: Texte BLEU = à saisir. Texte NOIR = calculé. Texte VERT = repris d’un autre onglet. Case JAUNE = sélecteur à changer.
A5: 1. Paramètres : ton épargne de départ, ton objectif mensuel, tes catégories et leurs budgets. Les valeurs de paie viennent de la fiche de septembre 2026 et restent à vérifier.
A6: 2. Mois : une ligne par mois (format 2026-10). Saisis le « Net reçu » dès la paie ; vide = estimation marquée « ≈ estimé ».
A7: 3. Charges : une ligne par charge et par mois. Mets « Oui » dans « Payée » quand elle est prélevée.
A8: 4. Dépenses : date, montant, catégorie. Une date future = dépense prévue (surlignée en orange), déjà déduite du reste à vivre.
A9: 5. Épargne : note chaque virement dans « Versements ». Pour affecter de l’argent à un objectif, ajoute un mouvement (+) ; pour en retirer, un mouvement (−).
A10: L’argent affecté fait partie de l’épargne totale : il n’est jamais compté deux fois. Si l’épargne libre devient négative, un message rouge le signale.
A11: 6. Tableau de bord : choisis le mois en B3. Comparer : choisis deux mois en B4 et B5.
A12: Règles de calcul (identiques à l’application Ma Paie) : reste à vivre = salaire − charges − épargne retenue − toutes les dépenses du mois (faites et prévues).
A13: Épargne retenue : mois terminé = épargne versée ; mois en cours ou à venir = le plus grand entre prévue et versée.
